setup.py
ci/__init__.py
ci/cli.py
ci/deployment.py
ci/probe.py
octopus_ci.egg-info/PKG-INFO
octopus_ci.egg-info/SOURCES.txt
octopus_ci.egg-info/dependency_links.txt
octopus_ci.egg-info/entry_points.txt
octopus_ci.egg-info/requires.txt
octopus_ci.egg-info/top_level.txt