Metadata-Version: 1.1
Name: octopus-ci
Version: 0.1.8
Summary: Bunch of commands to help continuous integration
Home-page: https://github.com/psycho-ir/octopus-ci
Author: Soroosh Sarabadani
Author-email: soroosh.sarabadani@zalando.de
License: UNKNOWN
Keywords: ci tools, probe port
Platform: UNKNOWN
Classifier: Development Status :: 3 - Alpha
Classifier: Environment :: Console
Classifier: Intended Audience :: Developers
Classifier: Intended Audience :: System Administrators
Classifier: License :: OSI Approved :: Apache Software License
Classifier: Operating System :: POSIX :: Linux
Classifier: Programming Language :: Python
Classifier: Programming Language :: Python :: 3.4
Classifier: Programming Language :: Python :: Implementation :: CPython
